MANIFEST.in
README.rst
nose_plugin.py
setup.cfg
setup.py
doctest_ignore_unicode.egg-info/PKG-INFO
doctest_ignore_unicode.egg-info/SOURCES.txt
doctest_ignore_unicode.egg-info/dependency_links.txt
doctest_ignore_unicode.egg-info/entry_points.txt
doctest_ignore_unicode.egg-info/not-zip-safe
doctest_ignore_unicode.egg-info/requires.txt
doctest_ignore_unicode.egg-info/top_level.txt