Metadata-Version: 1.1
Name: doctest-ignore-unicode
Version: 0.1.2
Summary: Add flag to ignore unicode literal prefixes in doctests
Home-page: http://github.com/gnublade/doctest-ignore-unicode
Author: Andy Kilner
Author-email: gnublde@gmail.com
License: Apache License, Version 2.0
Platform: UNKNOWN
Classifier: Development Status :: 3 - Alpha
Classifier: Operating System :: OS Independent
Classifier: Programming Language :: Python
Classifier: Intended Audience :: Developers
Classifier: License :: OSI Approved :: Apache Software License
Classifier: Topic :: Software Development :: Testing
